LICENSE
README.md
setup.py
src/Qciscirq.egg-info/PKG-INFO
src/Qciscirq.egg-info/SOURCES.txt
src/Qciscirq.egg-info/dependency_links.txt
src/Qciscirq.egg-info/requires.txt
src/Qciscirq.egg-info/top_level.txt
src/qciscirq/__init__.py
src/qciscirq/context.py
src/qciscirq/convert_cirq_to_qcis.py
src/qciscirq/convert_qcis_to_cirq.py
src/qciscirq/dynamical_decoupling.py
src/qciscirq/gate_table.py