Metadata-Version: 2.1
Name: Qciscirq
Version: 0.1b0
Summary: Adaptor between QCIS and Cirq
Home-page: 
Author: Yiming Zhang
Author-email: zhangyiming21@mail.ustc.edu.cn
License: MIT
Requires-Python: >=3.8.0
License-File: LICENSE
